data_retrieval/__init__.py
data_retrieval/py.typed
data_retrieval/data_provider/__init__.py
data_retrieval/data_provider/database/__init__.py
data_retrieval/data_provider/database/database_data_provider.py
data_retrieval/data_provider/database/sqlite3_data_provider.py
data_retrieval/data_provider/rest_api/__init__.py
data_retrieval/data_provider/rest_api/rest_api_data_provider.py
data_retrieval/foreign_exchange/__init__.py
data_retrieval/foreign_exchange/forex_data_provider_base.py
data_retrieval/foreign_exchange/forex_data_provider_wrapper.py
data_retrieval/foreign_exchange/forex_python_data_provider.py
data_retrieval/model/__init__.py
data_retrieval/model/data_module.py
data_retrieval/model/data_provider.py
data_retrieval/model/data_provider_wrapper.py
data_retrieval/model/exceptions.py
data_retrieval/utils/__init__.py
data_retrieval/utils/date_utils.py
data_retrieval_module-1.0.2.dist-info/licenses/LICENSE
data_retrieval_module-1.0.2.dist-info/METADATA
data_retrieval_module-1.0.2.dist-info/WHEEL
data_retrieval_module-1.0.2.dist-info/top_level.txt
data_retrieval_module-1.0.2.dist-info/RECORD
