Metadata-Version: 2.4
Name: data-retrieval-module
Version: 1.0.2
Summary: A standardized interface for data providers with sync and async support
Author-email: AbigailWilliams1692 <abigail.williams@example.com>
Maintainer-email: AbigailWilliams1692 <abigail.williams@example.com>
License-Expression: MIT
Project-URL: Homepage, https://github.com/AbigailWilliams1692/data-retrieval-module
Project-URL: Documentation, https://github.com/AbigailWilliams1692/data-retrieval-module/wiki
Project-URL: Repository, https://github.com/AbigailWilliams1692/data-retrieval-module
Project-URL: Bug Tracker, https://github.com/AbigailWilliams1692/data-retrieval-module/issues
Project-URL: Changelog, https://github.com/AbigailWilliams1692/data-retrieval-module/blob/main/CHANGELOG.md
Keywords: data,retrieval,provider,async,sync,database,api
Classifier: Development Status :: 4 - Beta
Classifier: Intended Audience :: Developers
Classifier: Operating System :: OS Independent
Classifier: Programming Language :: Python :: 3
Classifier: Programming Language :: Python :: 3.8
Classifier: Programming Language :: Python :: 3.9
Classifier: Programming Language :: Python :: 3.10
Classifier: Programming Language :: Python :: 3.11
Classifier: Programming Language :: Python :: 3.12
Classifier: Topic :: Software Development :: Libraries :: Python Modules
Classifier: Topic :: Database
Classifier: Topic :: Internet :: WWW/HTTP
Classifier: Typing :: Typed
Requires-Python: >=3.8
License-File: LICENSE
Requires-Dist: typing-extensions>=4.0.0; python_version < "3.10"
Requires-Dist: forex-python>=1.0.0
Provides-Extra: dev
Requires-Dist: pytest>=7.0.0; extra == "dev"
Requires-Dist: pytest-asyncio>=0.21.0; extra == "dev"
Requires-Dist: pytest-cov>=4.0.0; extra == "dev"
Requires-Dist: pytest-mock>=3.10.0; extra == "dev"
Requires-Dist: black>=23.0.0; extra == "dev"
Requires-Dist: flake8>=6.0.0; extra == "dev"
Requires-Dist: mypy>=1.0.0; extra == "dev"
Requires-Dist: isort>=5.12.0; extra == "dev"
Provides-Extra: async
Requires-Dist: aiohttp>=3.8.0; extra == "async"
Requires-Dist: aiosqlite>=0.19.0; extra == "async"
Requires-Dist: asyncpg>=0.28.0; extra == "async"
Provides-Extra: database
Requires-Dist: psycopg2-binary>=2.9.0; extra == "database"
Requires-Dist: PyMySQL>=1.0.0; extra == "database"
Provides-Extra: all
Requires-Dist: pytest>=7.0.0; extra == "all"
Requires-Dist: pytest-asyncio>=0.21.0; extra == "all"
Requires-Dist: pytest-cov>=4.0.0; extra == "all"
Requires-Dist: pytest-mock>=3.10.0; extra == "all"
Requires-Dist: black>=23.0.0; extra == "all"
Requires-Dist: flake8>=6.0.0; extra == "all"
Requires-Dist: mypy>=1.0.0; extra == "all"
Requires-Dist: isort>=5.12.0; extra == "all"
Requires-Dist: aiohttp>=3.8.0; extra == "all"
Requires-Dist: aiosqlite>=0.19.0; extra == "all"
Requires-Dist: asyncpg>=0.28.0; extra == "all"
Requires-Dist: psycopg2-binary>=2.9.0; extra == "all"
Requires-Dist: PyMySQL>=1.0.0; extra == "all"
Dynamic: license-file
